setup.py
funniest3D/__init__.py
funniest3D.egg-info/PKG-INFO
funniest3D.egg-info/SOURCES.txt
funniest3D.egg-info/dependency_links.txt
funniest3D.egg-info/not-zip-safe
funniest3D.egg-info/top_level.txt