Metadata-Version: 1.0
Name: funniest3D
Version: 0.1
Summary: The funniest joke in the world
Home-page: http://github.com/storborg/funniest3D
Author: Flying Circus
Author-email: pakpoomton@gmail.com
License: MIT
Platform: UNKNOWN
